zint/__init__.py
zint/zint.py
zint-1.2.dist-info/LICENSE.rst
zint-1.2.dist-info/METADATA
zint-1.2.dist-info/WHEEL
zint-1.2.dist-info/top_level.txt
zint-1.2.dist-info/RECORD
