Metadata-Version: 2.1
Name: zint
Version: 1.2
Summary: Python ctypes interface to libzint
Home-page: http://github.com/jmptbl/python-zint
Author: Aragon Gouveia
Author-email: aragon@phat.za.net
License: BSD
Keywords: zint ctypes
Platform: UNKNOWN
